slack_messages/__init__.py
slack_messages/log.py
slack_exception_messages-0.1.dist-info/LICENSE
slack_exception_messages-0.1.dist-info/METADATA
slack_exception_messages-0.1.dist-info/WHEEL
slack_exception_messages-0.1.dist-info/top_level.txt
slack_exception_messages-0.1.dist-info/RECORD
