Metadata-Version: 2.1
Name: slack-exception-messages
Version: 0.1
Summary: A package that enables you to easily exception messages from django to slack
Requires-Python: >=3.6
License-File: LICENSE
Requires-Dist: slack-sdk (>=3.13.0)
